specifind/__init__.py
specifind/components/__init__.py
specifind/components/coref.py
specifind/components/ner.py
specifind/components/re.py
specifind/components/senter.py
specifind/specifind.py
specifind/vendor/__init__.py
specifind/vendor/wtpsplit/__init__.py
specifind/vendor/wtpsplit/configs.py
specifind/vendor/wtpsplit/data/__init__.py
specifind/vendor/wtpsplit/data/language_info.csv
specifind/vendor/wtpsplit/data/punctuation.json
specifind/vendor/wtpsplit/data/punctuation.txt
specifind/vendor/wtpsplit/data/punctuation_xlmr.txt
specifind/vendor/wtpsplit/data/punctuation_xlmr_unk.txt
specifind/vendor/wtpsplit/data_acquisition/__init__.py
specifind/vendor/wtpsplit/data_acquisition/extract_all_data.py
specifind/vendor/wtpsplit/data_acquisition/extract_eval_data.py
specifind/vendor/wtpsplit/data_acquisition/extract_sentences.py
specifind/vendor/wtpsplit/data_acquisition/extract_shared_task_data.py
specifind/vendor/wtpsplit/evaluation/__init__.py
specifind/vendor/wtpsplit/evaluation/adapt.py
specifind/vendor/wtpsplit/evaluation/evaluate_sepp_nlg_subtask1.py
specifind/vendor/wtpsplit/evaluation/evaluation_results/lyrics/command-r.json
specifind/vendor/wtpsplit/evaluation/evaluation_results/lyrics/llama-3.json
specifind/vendor/wtpsplit/evaluation/evaluation_results/lyrics/sat-12l_lora.json
specifind/vendor/wtpsplit/evaluation/evaluation_results/lyrics/sat-12l_lora_no_pretraining.json
specifind/vendor/wtpsplit/evaluation/evaluation_results/lyrics/sat-12l_lora_no_pretraining_s100.json
specifind/vendor/wtpsplit/evaluation/evaluation_results/lyrics/sat-12l_lora_no_pretraining_s1000.json
specifind/vendor/wtpsplit/evaluation/evaluation_results/lyrics/sat-12l_lora_s100.json
specifind/vendor/wtpsplit/evaluation/evaluation_results/lyrics/sat-12l_lora_s1000.json
specifind/vendor/wtpsplit/evaluation/evaluation_results/lyrics/wtp-12l.json
specifind/vendor/wtpsplit/evaluation/evaluation_results/lyrics/wtp-12l_s100.json
specifind-0.2.0.dist-info/METADATA
specifind-0.2.0.dist-info/WHEEL
specifind-0.2.0.dist-info/RECORD
