Metadata-Version: 2.4
Name: specifind
Version: 0.2.0
Summary: Specifind: A Natural Language Processing Tool for Automating Species Occurrence (Re-)Discovery from Scientific Literature
License: GPL-3.0-or-later
Keywords: nlp,species,biodiversity,occurrence,entity-recognition,relation-extraction,scientific-literature,text-mining
Author: Tomás Golomb Durán
Author-email: tomasgduran@gmail.com
Requires-Python: >=3.10,<3.13
Classifier: Programming Language :: Python :: 3
Classifier: Programming Language :: Python :: 3.10
Classifier: Programming Language :: Python :: 3.11
Classifier: Programming Language :: Python :: 3.12
Classifier: License :: OSI Approved :: MIT License
Classifier: Operating System :: OS Independent
Classifier: Intended Audience :: Science/Research
Classifier: Topic :: Scientific/Engineering :: Information Analysis
Classifier: Topic :: Text Processing :: Linguistic
Classifier: Topic :: Scientific/Engineering :: Artificial Intelligence
Requires-Dist: cached_property (==2.0.1)
Requires-Dist: fastcoref (>=2.1.6,<3.0.0)
Requires-Dist: mosestokenizer (>=1.2.1,<2.0.0)
Requires-Dist: pymupdf (>=1.26.6,<2.0.0)
Requires-Dist: science-ocr (==0.3.0)
Requires-Dist: setuptools (>=80.3.1,<81.0.0)
Requires-Dist: skops (>=0.13.0,<0.14.0)
Requires-Dist: spacy (>=3.7.4,<4.0.0)
Requires-Dist: spacy-transformers-specifind (>=1.3.10,<2.0.0)
Requires-Dist: surya-ocr (==0.17.0)
Requires-Dist: torch (>=2.9,<3.0)
Requires-Dist: tqdm (>=4.66.4,<5.0.0)
Requires-Dist: transformers (>=4.56.1,<5.0.0)
Project-URL: Documentation, https://github.com/ToGo347/Specifind
Project-URL: Homepage, https://github.com/ToGo347/Specifind
Project-URL: Issues, https://github.com/ToGo347/Specifind/issues
Project-URL: Repository, https://github.com/ToGo347/Specifind
